pyskiplist/__init__.py
pyskiplist/dllist.py
pyskiplist/skiplist.py
pyskiplist-1.0.0.dist-info/top_level.txt
pyskiplist-1.0.0.dist-info/METADATA
pyskiplist-1.0.0.dist-info/DESCRIPTION.rst
pyskiplist-1.0.0.dist-info/metadata.json
pyskiplist-1.0.0.dist-info/WHEEL
pyskiplist-1.0.0.dist-info/RECORD
