Metadata-Version: 2.0
Name: pyskiplist
Version: 1.0.0
Summary: Fast, pure Python indexable skip list
Home-page: https://github.com/geertj/pyskiplist
Author: Geert Jansen
Author-email: geertj@gmail.com
License: MIT
Platform: UNKNOWN
Classifier: Development Status :: 5 - Production/Stable
Classifier: License :: OSI Approved :: MIT License
Classifier: Operating System :: POSIX
Classifier: Operating System :: Microsoft :: Windows
Classifier: Operating System :: MacOS :: MacOS X
Classifier: Programming Language :: Python :: 2.7
Classifier: Programming Language :: Python :: 3.3
Classifier: Programming Language :: Python :: 3.4
